{
  "Servers" : [ {
    "Category" : 0,
    "DomainOrIP" : "p16-va.tiktokcdn.com.prem1.teamuniversal-vpn.xyz",
    "Flag" : "sg",
    "Name" : "STORIES 1"
  }, {
    "Category" : 0,
    "DomainOrIP" : "p16-va.tiktokcdn.com.prem2.teamuniversal-vpn.xyz",
    "Flag" : "sg",
    "Name" : "STORIES 2"
  }, {
    "Category" : 0,
    "DomainOrIP" : "p16-va.tiktokcdn.com.prem3.teamuniversal-vpn.xyz",
    "Flag" : "sg",
    "Name" : "STORIES 3"
  }, {
    "Category" : 0,
    "DomainOrIP" : "p16-va.tiktokcdn.com.prem4.teamuniversal-vpn.xyz",
    "Flag" : "sg",
    "Name" : "STORIES 4"
  }, {
    "Category" : 0,
    "DomainOrIP" : "p16-va.tiktokcdn.com.prem5.teamuniversal-vpn.xyz",
    "Flag" : "in",
    "Name" : "STORIES 5"
  }, {
    "Category" : 0,
    "DomainOrIP" : "p16-va.tiktokcdn.com.prem6.teamuniversal-vpn.xyz",
    "Flag" : "in",
    "Name" : "STORIES 6"
  }, {
    "Category" : 0,
    "DomainOrIP" : "p16-va.tiktokcdn.com.prem7.teamuniversal-vpn.xyz",
    "Flag" : "us",
    "Name" : "STORIES 7"
  }, {
    "Category" : 0,
    "DomainOrIP" : "p16-va.tiktokcdn.com.prem8.teamuniversal-vpn.xyz",
    "Flag" : "us",
    "Name" : "STORIES 8"
  }, {
    "Category" : 0,
    "DomainOrIP" : "p16-va.tiktokcdn.com.prem9.teamuniversal-vpn.xyz",
    "Flag" : "us",
    "Name" : "STORIES 9"
  }, {
    "Category" : 1,
    "DomainOrIP" : "p16-va.tiktokcdn.com.vip1.teamuniversal-vpn.xyz",
    "Flag" : "sg",
    "Name" : "STORIES 1"
  }, {
    "Category" : 1,
    "DomainOrIP" : "p16-va.tiktokcdn.com.vip2.teamuniversal-vpn.xyz",
    "Flag" : "sg",
    "Name" : "STORIES 2"
  }, {
    "Category" : 1,
    "DomainOrIP" : "p16-va.tiktokcdn.com.vip3.teamuniversal-vpn.xyz",
    "Flag" : "sg",
    "Name" : "STORIES 3"
  }, {
    "Category" : 1,
    "DomainOrIP" : "p16-va.tiktokcdn.com.vip4.teamuniversal-vpn.xyz",
    "Flag" : "sg",
    "Name" : "STORIES 4"
  }, {
    "Category" : 1,
    "DomainOrIP" : "p16-va.tiktokcdn.com.vip5.teamuniversal-vpn.xyz",
    "Flag" : "sg",
    "Name" : "STORIES 5"
  }, {
    "Category" : 1,
    "DomainOrIP" : "p16-va.tiktokcdn.com.vip6.teamuniversal-vpn.xyz",
    "Flag" : "in",
    "Name" : "STORIES 6"
  }, {
    "Category" : 1,
    "DomainOrIP" : "p16-va.tiktokcdn.com.vip7.teamuniversal-vpn.xyz",
    "Flag" : "in",
    "Name" : "STORIES 7"
  }, {
    "Category" : 1,
    "DomainOrIP" : "p16-va.tiktokcdn.com.vip8.teamuniversal-vpn.xyz",
    "Flag" : "us",
    "Name" : "STORIES 8"
  }, {
    "Category" : 1,
    "DomainOrIP" : "p16-va.tiktokcdn.com.vip9.teamuniversal-vpn.xyz",
    "Flag" : "us",
    "Name" : "STORIES 9"
  }, {
    "Category" : 2,
    "DomainOrIP" : "p16-va.tiktokcdn.com.priv1.teamuniversal-vpn.xyz",
    "Flag" : "sg",
    "Name" : "STORIES 1"
  }, {
    "Category" : 2,
    "DomainOrIP" : "p16-va.tiktokcdn.com.priv2.teamuniversal-vpn.xyz",
    "Flag" : "sg",
    "Name" : "STORIES 2"
  }, {
    "Category" : 2,
    "DomainOrIP" : "p16-va.tiktokcdn.com.priv3.teamuniversal-vpn.xyz",
    "Flag" : "sg",
    "Name" : "STORIES 3"
  }, {
    "Category" : 2,
    "DomainOrIP" : "p16-va.tiktokcdn.com.priv4.teamuniversal-vpn.xyz",
    "Flag" : "sg",
    "Name" : "STORIES 4"
  }, {
    "Category" : 2,
    "DomainOrIP" : "p16-va.tiktokcdn.com.priv5.teamuniversal-vpn.xyz",
    "Flag" : "sg",
    "Name" : "STORIES 5"
  }, {
    "Category" : 2,
    "DomainOrIP" : "p16-va.tiktokcdn.com.priv6.teamuniversal-vpn.xyz",
    "Flag" : "in",
    "Name" : "STORIES 6"
  }, {
    "Category" : 2,
    "DomainOrIP" : "p16-va.tiktokcdn.com.priv7.teamuniversal-vpn.xyz",
    "Flag" : "in",
    "Name" : "STORIES 7"
  }, {
    "Category" : 2,
    "DomainOrIP" : "p16-va.tiktokcdn.com.priv8.teamuniversal-vpn.xyz",
    "Flag" : "us",
    "Name" : "STORIES 8"
  }, {
    "Category" : 2,
    "DomainOrIP" : "p16-va.tiktokcdn.com.priv9.teamuniversal-vpn.xyz",
    "Flag" : "us",
    "Name" : "STORIES 9"
  }, {
    "Category" : 0,
    "DomainOrIP" : "staging.iwant.ph.prem1.teamuniversal-vpn.xyz",
    "Flag" : "de",
    "Name" : "GIGAVIDEOS 1"
  }, {
    "Category" : 0,
    "DomainOrIP" : "staging.iwant.ph.prem2.teamuniversal-vpn.xyz",
    "Flag" : "de",
    "Name" : "GIGAVIDEOS 2"
  }, {
    "Category" : 0,
    "DomainOrIP" : "activity.mobilelegends.com.prem1.teamuniversal-vpn.xyz",
    "Flag" : "gb",
    "Name" : "GIGAGAMES/ML10 1"
  }, {
    "Category" : 0,
    "DomainOrIP" : "activity.mobilelegends.com.prem2.teamuniversal-vpn.xyz",
    "Flag" : "gb",
    "Name" : "GIGAGAMES/ML10 2"
  }, {
    "Category" : 0,
    "DomainOrIP" : "www.google-analytics.com.prem1.teamuniversal-vpn.xyz",
    "Flag" : "gb",
    "Name" : "GIGAWORK/STUDY 1"
  }, {
    "Category" : 1,
    "DomainOrIP" : "www.google-analytics.com.prem2.teamuniversal-vpn.xyz",
    "Flag" : "sg",
    "Name" : "GIGAWORK/STUDY 2"
  }, {
    "Category" : 1,
    "DomainOrIP" : "staging.iwant.ph.vip1.teamuniversal-vpn.xyz",
    "Flag" : "de",
    "Name" : "GIGAVIDEOS 1"
  }, {
    "Category" : 1,
    "DomainOrIP" : "staging.iwant.ph.vip2.teamuniversal-vpn.xyz",
    "Flag" : "gb",
    "Name" : "GIGAVIDEOS 2"
  }, {
    "Category" : 1,
    "DomainOrIP" : "activity.mobilelegends.com.vip1.teamuniversal-vpn.xyz",
    "Flag" : "gb",
    "Name" : "GIGAGAMES/ML10 1"
  }, {
    "Category" : 1,
    "DomainOrIP" : "activity.mobilelegends.com.vip1.teamuniversal-vpn.xyz",
    "Flag" : "gb",
    "Name" : "GIGAGAMES/ML10 2"
  }, {
    "Category" : 2,
    "DomainOrIP" : "www.google-analytics.com.vip1.teamuniversal-vpn.xyz",
    "Flag" : "de",
    "Name" : "GIGAWORK/STUDY 1"
  }, {
    "Category" : 2,
    "DomainOrIP" : "www.google-analytics.com.vip2.teamuniversal-vpn.xyz",
    "Flag" : "de",
    "Name" : "GIGAWORK/STUDY 2"
  }, {
    "Category" : 2,
    "DomainOrIP" : "staging.iwant.ph.priv1.teamuniversal-vpn.xyz",
    "Flag" : "gb",
    "Name" : "GIGAVIDEOS 1"
  }, {
    "Category" : 2,
    "DomainOrIP" : "staging.iwant.ph.priv2.teamuniversal-vpn.xyz",
    "Flag" : "gb",
    "Name" : "GIGAVIDEOS 2"
  }, {
    "Category" : 2,
    "DomainOrIP" : "activity.mobilelegends.com.priv1.teamuniversal-vpn.xyz",
    "Flag" : "gb",
    "Name" : "GIGAGAMES/ML10 1"
  }, {
    "Category" : 2,
    "DomainOrIP" : "activity.mobilelegends.com.priv2.teamuniversal-vpn.xyz",
    "Flag" : "us",
    "Name" : "GIGAGAMES/ML10 2"
  }, {
    "Category" : 0,
    "DomainOrIP" : "e9413.g.akamaiedge.net.prem1.teamuniversal-vpn.xyz",
    "Flag" : "sg",
    "Name" : "SUN FIX PLAN SERVER 1"
  }, {
    "Category" : 0,
    "DomainOrIP" : "e9413.g.akamaiedge.net.prem2.teamuniversal-vpn.xyz",
    "Flag" : "sg",
    "Name" : "SUN FIX PLAN SERVER 2"
  }, {
    "Category" : 0,
    "DomainOrIP" : "e9413.g.akamaiedge.net.prem3.teamuniversal-vpn.xyz",
    "Flag" : "sg",
    "Name" : "SUN FIX PLAN SERVER 3"
  }, {
    "Category" : 0,
    "DomainOrIP" : "e9413.g.akamaiedge.net.prem4.teamuniversal-vpn.xyz",
    "Flag" : "sg",
    "Name" : "SUN FIX PLAN SERVER 4"
  }, {
    "Category" : 0,
    "DomainOrIP" : "e9413.g.akamaiedge.net.prem5.teamuniversal-vpn.xyz",
    "Flag" : "sg",
    "Name" : "SUN FIX PLAN SERVER 5"
  }, {
    "Category" : 1,
    "DomainOrIP" : "e9413.g.akamaiedge.net.vip1.teamuniversal-vpn.xyz",
    "Flag" : "sg",
    "Name" : "SUN FIX PLAN SERVER 1"
  }, {
    "Category" : 1,
    "DomainOrIP" : "e9413.g.akamaiedge.net.vip2.teamuniversal-vpn.xyz",
    "Flag" : "sg",
    "Name" : "SUN FIX PLAN SERVER 2"
  }, {
    "Category" : 1,
    "DomainOrIP" : "e9413.g.akamaiedge.net.vip3.teamuniversal-vpn.xyz",
    "Flag" : "sg",
    "Name" : "SUN FIX PLAN SERVER 3"
  }, {
    "Category" : 1,
    "DomainOrIP" : "e9413.g.akamaiedge.net.vip4.teamuniversal-vpn.xyz",
    "Flag" : "sg",
    "Name" : "SUN FIX PLAN SERVER 4"
  }, {
    "Category" : 1,
    "DomainOrIP" : "e9413.g.akamaiedge.net.vip5.teamuniversal-vpn.xyz",
    "Flag" : "sg",
    "Name" : "SUN FIX PLAN SERVER 5"
  }, {
    "Category" : 2,
    "DomainOrIP" : "e9413.g.akamaiedge.net.priv1.teamuniversal-vpn.xyz",
    "Flag" : "sg",
    "Name" : "SUN FIX PLAN SERVER 1"
  }, {
    "Category" : 2,
    "DomainOrIP" : "e9413.g.akamaiedge.net.priv2.teamuniversal-vpn.xyz",
    "Flag" : "sg",
    "Name" : "SUN FIX PLAN SERVER 2"
  }, {
    "Category" : 2,
    "DomainOrIP" : "e9413.g.akamaiedge.net.priv3.teamuniversal-vpn.xyz",
    "Flag" : "sg",
    "Name" : "SUN FIX PLAN SERVER 3"
  }, {
    "Category" : 2,
    "DomainOrIP" : "e9413.g.akamaiedge.net.priv4.teamuniversal-vpn.xyz",
    "Flag" : "sg",
    "Name" : "SUN FIX PLAN SERVER 4"
  }, {
    "Category" : 2,
    "DomainOrIP" : "e9413.g.akamaiedge.net.priv5.teamuniversal-vpn.xyz",
    "Flag" : "sg",
    "Name" : "SUN FIX PLAN SERVER 5"
  }, {
    "Category" : 0,
    "DomainOrIP" : "www.google-analytics.com.prem1.teamuniversal-vpn.xyz",
    "Flag" : "sg",
    "Name" : "GTM PROMOS 1"
  }, {
    "Category" : 0,
    "DomainOrIP" : "www.google-analytics.com.prem2.teamuniversal-vpn.xyz",
    "Flag" : "sg",
    "Name" : "GTM PROMOS 2"
  }, {
    "Category" : 0,
    "DomainOrIP" : "www.google-analytics.com.prem3.teamuniversal-vpn.xyz",
    "Flag" : "sg",
    "Name" : "GTM PROMOS 3"
  }, {
    "Category" : 0,
    "DomainOrIP" : "www.google-analytics.com.prem4.teamuniversal-vpn.xyz",
    "Flag" : "sg",
    "Name" : "GTM PROMOS 4"
  }, {
    "Category" : 0,
    "DomainOrIP" : "www.google-analytics.com.prem5.teamuniversal-vpn.xyz",
    "Flag" : "sg",
    "Name" : "GTM PROMOS 5"
  }, {
    "Category" : 1,
    "DomainOrIP" : "www.google-analytics.com.vip1.teamuniversal-vpn.xyz",
    "Flag" : "sg",
    "Name" : "GTM PROMOS 1"
  }, {
    "Category" : 1,
    "DomainOrIP" : "www.google-analytics.com.vip2.teamuniversal-vpn.xyz",
    "Flag" : "sg",
    "Name" : "GTM PROMOS 2"
  }, {
    "Category" : 1,
    "DomainOrIP" : "www.google-analytics.com.vip3.teamuniversal-vpn.xyz",
    "Flag" : "sg",
    "Name" : "GTM PROMOS 3"
  }, {
    "Category" : 1,
    "DomainOrIP" : "www.google-analytics.com.vip4.teamuniversal-vpn.xyz",
    "Flag" : "sg",
    "Name" : "GTM PROMOS 4"
  }, {
    "Category" : 1,
    "DomainOrIP" : "www.google-analytics.com.vip5.teamuniversal-vpn.xyz",
    "Flag" : "sg",
    "Name" : "GTM PROMOS 5"
  }, {
    "Category" : 2,
    "DomainOrIP" : "www.google-analytics.com.priv1.teamuniversal-vpn.xyz",
    "Flag" : "sg",
    "Name" : "GTM PROMOS 1"
  }, {
    "Category" : 2,
    "DomainOrIP" : "www.google-analytics.com.priv2.teamuniversal-vpn.xyz",
    "Flag" : "sg",
    "Name" : "GTM PROMOS 2"
  }, {
    "Category" : 2,
    "DomainOrIP" : "www.google-analytics.com.priv3.teamuniversal-vpn.xyz",
    "Flag" : "sg",
    "Name" : "GTM PROMOS 3"
  }, {
    "Category" : 2,
    "DomainOrIP" : "www.google-analytics.com.priv4.teamuniversal-vpn.xyz",
    "Flag" : "sg",
    "Name" : "GTM PROMOS 4"
  }, {
    "Category" : 2,
    "DomainOrIP" : "www.google-analytics.com.priv5.teamuniversal-vpn.xyz",
    "Flag" : "sg",
    "Name" : "GTM PROMOS 5"
  }, {
    "Category" : 2,
    "DomainOrIP" : "www.google-analytics.com.priv1.teamuniversal-vpn.xyz",
    "Flag" : "sg",
    "Name" : "GIGAWORK/STUDY 1"
  }, {
    "Category" : 2,
    "DomainOrIP" : "www.google-analytics.com.priv2.teamuniversal-vpn.xyz",
    "Flag" : "sg",
    "Name" : "GIGAWORK/STUDY 2"
  }, {
    "Category" : 2,
    "DomainOrIP" : "p16-va.tiktokcdn.com.ph1.teamuniversal-vpn.xyz",
    "Flag" : "ph",
    "Name" : "GIGASTORIES PH1"
  }, {
    "Category" : 2,
    "DomainOrIP" : "p16-va.tiktokcdn.com.ph2.teamuniversal-vpn.xyz",
    "Flag" : "ph",
    "Name" : "GIGASTORIES PH2"
  }, {
    "Category" : 2,
    "DomainOrIP" : "staging.iwant.ph.ph1.teamuniversal-vpn.xyz",
    "Flag" : "ph",
    "Name" : "GIGAVIDEOS PH1"
  }, {
    "Category" : 2,
    "DomainOrIP" : "staging.iwant.ph.ph2.teamuniversal-vpn.xyz",
    "Flag" : "ph",
    "Name" : "GIGAVIDEOS PH2"
  }, {
    "Category" : 2,
    "DomainOrIP" : "e9413.g.akamaiedge.net.ph1.teamuniversal-vpn.xyz",
    "Flag" : "ph",
    "Name" : "SUN/FLP PH1"
  }, {
    "Category" : 2,
    "DomainOrIP" : "e9413.g.akamaiedge.net.ph2.teamuniversal-vpn.xyz",
    "Flag" : "ph",
    "Name" : "SUN/FLP PH2"
  }, {
    "Category" : 2,
    "DomainOrIP" : "activity.mobilelegends.com.ph1.teamuniversal-vpn.xyz",
    "Flag" : "ph",
    "Name" : "GIGAGAMES/ML10 1"
  }, {
    "Category" : 2,
    "DomainOrIP" : "activity.mobilelegends.com.ph2.teamuniversal-vpn.xyz",
    "Flag" : "ph",
    "Name" : "GIGAGAMES/ML10 2"
  }, {
    "Category" : 2,
    "DomainOrIP" : "www.google-analytics.com.ph1.teamuniversal-vpn.xyz",
    "Flag" : "ph",
    "Name" : "GIGAWORK/STUDY 1"
  }, {
    "Category" : 2,
    "DomainOrIP" : "www.google-analytics.com.ph2.teamuniversal-vpn.xyz",
    "Flag" : "ph",
    "Name" : "GIGAWORK/STUDY 2"
  }, {
    "Category" : 2,
    "DomainOrIP" : "p16-va.tiktokcdn.com.nlfx1.teamuniversal-vpn.xyz",
    "Flag" : "us",
    "Name" : "GIGASTORIES NETFLIX 1"
  }, {
    "Category" : 2,
    "DomainOrIP" : "p16-va.tiktokcdn.com.nlfx2.teamuniversal-vpn.xyz",
    "Flag" : "us",
    "Name" : "GIGASTORIES NETFLIX 2"
  }, {
    "Category" : 2,
    "DomainOrIP" : "e9413.g.akamaiedge.net.nlfx1.teamuniversal-vpn.xyz",
    "Flag" : "us",
    "Name" : "SUN/FLP NETFLIX 1"
  }, {
    "Category" : 2,
    "DomainOrIP" : "e9413.g.akamaiedge.net.nlfx2.teamuniversal-vpn.xyz",
    "Flag" : "us",
    "Name" : "SUN/FLP NETFLIX 2"
  } ],
  "Payloads" : [ {
    "Format" : 1,
    "ForwardHost" : true,
    "FullHost" : false,
    "Host" : "pHTy7kVaPBtUDFebj2x4/ZKef5vcEUFcVbuP87cxsm03/citkw21WxRViONF7hjw8OV+FeVplvM16CQWTsKgHw==",
    "Name" : "\uD83C\uDDF5\uD83C\uDDEDSUN/CTC/TU/FLP 1",
    "OnlineHost" : true,
    "Port" : 8080,
    "Proxy" : "",
    "ReverseProxy" : false,
    "ShowText" : true,
    "Text" : "enjoy!!!!",
    "UseDefaultProxy" : true
  }, {
    "Format" : 3,
    "ForwardHost" : false,
    "FullHost" : true,
    "Host" : "jll1bzUcpqkjTvC1iaSL4DDp/mB8vU9+KYH+bGqNAZg6jkMlDIWS7ukzCtP3zdYKyktfsPv8C7GNt+utE07QyTcNnCXVYXtFnLhsuas+1BSz23jamtkjVOz5F/HG5WlR",
    "Name" : "\uD83C\uDDF5\uD83C\uDDEDSUN/CTC/TU/FLP 2",
    "OnlineHost" : true,
    "Port" : 8080,
    "Proxy" : "",
    "ReverseProxy" : false,
    "ShowText" : false,
    "Text" : "",
    "UseDefaultProxy" : true
  }, {
    "Format" : 1,
    "ForwardHost" : true,
    "FullHost" : false,
    "Host" : "dwTN4iEFv4c9dRsDDLpi+Ye9QRD5A9LZMwZl/zmfgi0KAjpHeI4JX21Xa/wui9ULQpQmhioWAHXpxyU3wyEbANY0B5rJI1tUWJKM+J4SqxzrRWxBxWMCjjD7fYj9vH7L",
    "Name" : "\uD83C\uDDF5\uD83C\uDDED SUN TU200 1",
    "OnlineHost" : true,
    "Port" : 8080,
    "Proxy" : "",
    "ReverseProxy" : false,
    "ShowText" : false,
    "Text" : "",
    "UseDefaultProxy" : true
  }, {
    "Format" : 3,
    "ForwardHost" : false,
    "FullHost" : true,
    "Host" : "XxR80La75IlxtdoM5o8rvb6fgeIdpjSPLS6cKV0g6VQauS/UWfRqLQhLGtoO6wwUCxmjfwFeyUGTWJURQx6yeyNEt7N3RNRvYhgm2Px17gRvZUgYjZwynCuxfXK1u/N6",
    "Name" : "\uD83C\uDDF5\uD83C\uDDED SUN TU200 2",
    "OnlineHost" : true,
    "Port" : 8080,
    "Proxy" : "",
    "ReverseProxy" : false,
    "ShowText" : false,
    "Text" : "",
    "UseDefaultProxy" : true
  }, {
    "Format" : 1,
    "ForwardHost" : true,
    "FullHost" : false,
    "Host" : "fN9EecaOZDotqpTe3gJcwsHhg3A8g9IXNy5AJP1L0K3ootQNko++u+ezg5Y9u0lw9QjIXqgeOduAwYAb/SukwQ==",
    "Name" : "\uD83C\uDDF5\uD83C\uDDED GLOBE/TM GOWATCH",
    "OnlineHost" : true,
    "Port" : 8080,
    "Proxy" : "",
    "ReverseProxy" : false,
    "ShowText" : false,
    "Text" : "",
    "UseDefaultProxy" : true
  }, {
    "Format" : 1,
    "ForwardHost" : true,
    "FullHost" : false,
    "Host" : "rmYfPhQkXWkBc45xAB68htph7kN8Rvi/z8L2Yeor1aBAJO3khtSXyYHe6JE8olaN",
    "Name" : "\uD83C\uDDF5\uD83C\uDDED FUN-ARAL/FUN-SAGAD",
    "OnlineHost" : true,
    "Port" : 8080,
    "Proxy" : "",
    "ReverseProxy" : false,
    "ShowText" : false,
    "Text" : "",
    "UseDefaultProxy" : true
  }, {
    "Format" : 1,
    "ForwardHost" : true,
    "FullHost" : false,
    "Host" : "jCmF+b0CDtT1Q8OK5EJSs+pMC1nTSHaDx/fSBLhioupbFY3TwmXKeVGzUgkE9RR94b5Po6lPXUHzcRf0lJPkLbUxQIrfGe93WQrydMRe01g=",
    "Name" : "Fun-aliw TNT any promo",
    "OnlineHost" : true,
    "Port" : 8080,
    "Proxy" : "",
    "ReverseProxy" : false,
    "ShowText" : false,
    "Text" : "",
    "UseDefaultProxy" : true
  }, {
    "Format" : 1,
    "ForwardHost" : true,
    "FullHost" : false,
    "Host" : "x+reHQzc9IcdTffn14vMM5QUsCgjkf1Q3BF9orP7MKoIETwo6jBGrZpKgMaxYZiMh8GdIDkbb4bndgrlrYGrStCCcweSw5Tgz2Fo6RYfV6R0FdFyE/F/ACbHzQ7chBDj",
    "Name" : "TNT games",
    "OnlineHost" : true,
    "Port" : 8080,
    "Proxy" : "",
    "ReverseProxy" : false,
    "ShowText" : false,
    "Text" : "",
    "UseDefaultProxy" : true
  }, {
    "Format" : 2,
    "ForwardHost" : false,
    "FullHost" : false,
    "Host" : "L9kYe/Dx96t5uxJ3ASJNGT7VJ93CwcZIkPjOo2L/FnAtpM3FFMn8PSAUP1qMthhLYU0XuufGY6xKEXa1JbwAeA==",
    "Name" : "\uD83C\uDDF5\uD83C\uDDED TNT-ML10 1",
    "OnlineHost" : false,
    "Port" : 8080,
    "Proxy" : "",
    "ReverseProxy" : false,
    "ShowText" : false,
    "Text" : "",
    "UseDefaultProxy" : true
  }, {
    "Format" : 3,
    "ForwardHost" : true,
    "FullHost" : false,
    "Host" : "rJ5kFzcWxHXH6jrfjaxniwBFs8DF92KRDJJUUdFfFxVpfQ1uesBWIVM0tO5Pz8MhJHvpXopeOxVp2HOIfu1FOg==",
    "Name" : "\uD83C\uDDF5\uD83C\uDDED TNT-ML10 2",
    "OnlineHost" : true,
    "Port" : 8080,
    "Proxy" : "",
    "ReverseProxy" : false,
    "ShowText" : false,
    "Text" : "",
    "UseDefaultProxy" : true
  }, {
    "Format" : 1,
    "ForwardHost" : true,
    "FullHost" : false,
    "Host" : "6TTu4M56XlizTVG3Qunh+fSrcJEnibnke1cHmLoGDiyUnyvEsctMagWcqdDtVL3uSpg4mRJSYi95fryUEvLkGA==",
    "Name" : "\uD83C\uDDF5\uD83C\uDDED GLOBE GOWATCH/WNP",
    "OnlineHost" : true,
    "Port" : 8080,
    "Proxy" : "",
    "ReverseProxy" : false,
    "ShowText" : false,
    "Text" : "",
    "UseDefaultProxy" : true
  }, {
    "Format" : 1,
    "ForwardHost" : true,
    "FullHost" : false,
    "Host" : "Pgc2KtMZj/cgpfxTbNek7eLgjlu4XtSNdbvnG1LvESkqvzG2szSOi5rxg5GQWqg+",
    "Name" : "\uD83C\uDDF5\uD83C\uDDED GTM GAMES99 1",
    "OnlineHost" : true,
    "Port" : 8080,
    "Proxy" : "",
    "ReverseProxy" : false,
    "ShowText" : false,
    "Text" : "",
    "UseDefaultProxy" : true
  }, {
    "Format" : 1,
    "ForwardHost" : true,
    "FullHost" : false,
    "Host" : "Jy8TtTuU75rJ1QqV2EFfPl2MM60Bx1SEynuTn5zxMu2SrOhJfJK30cuwawYxxC7QAC7130AAj6aufuLoq8V+qw==",
    "Name" : "\uD83C\uDDF5\uD83C\uDDED NEW STORIES",
    "OnlineHost" : true,
    "Port" : 8080,
    "Proxy" : "",
    "ReverseProxy" : false,
    "ShowText" : false,
    "Text" : "",
    "UseDefaultProxy" : true
  }, {
    "Format" : 3,
    "ForwardHost" : true,
    "FullHost" : false,
    "Host" : "9aXx3rA1GTmHRNzBS80GgwYwt9MVDxVQtpw2B3apYwKaR6/81ynx6soA6KQza3grr6dAK6GjR+OWdbM7GfV32tm148449xInjuQrrQF4TXs=",
    "Name" : "SMART AT10/AT60",
    "OnlineHost" : true,
    "Port" : 8080,
    "Proxy" : "6WAhmq1sSvi+ePVl1c5n2sIOaUVVPXi51OnwgTh87jn3iy3YwfMCUAGfzbSDnPvnY1CInNxHFZ7NyO7s/K7Dez8PH67rVN3aqQM8kM2ASWVFozRCztpMOalq9WkuhS7To+hgWGeLFj5uUHldNyMOow==",
    "ReverseProxy" : false,
    "ShowText" : false,
    "Text" : "",
    "UseDefaultProxy" : false
  }, {
    "Format" : 3,
    "ForwardHost" : false,
    "FullHost" : true,
    "Host" : "hS2msG2YrdV4Il4d5WluFYBP5Iwyjsoa7uCeq8pl8aaFpVsJpuYk4ogbv9dDeZ0QGYHaiqR3gIO89Ke5bTtbUXYqhsxkJB+tF68KvsEa70k0WEupS9IVhx5rdEE1Tbjv",
    "Name" : "SUN TU PROMO NEW 1",
    "OnlineHost" : true,
    "Port" : 8080,
    "Proxy" : "",
    "ReverseProxy" : false,
    "ShowText" : false,
    "Text" : "",
    "UseDefaultProxy" : true
  }, {
    "Format" : 2,
    "ForwardHost" : true,
    "FullHost" : false,
    "Host" : "48u5ID4Yrrkc4/5Paa6IOCDDdpWiYu6LKG40PNWtBI+ndOOUBA30oQhNxpWIJrFxGzRGMWFvMi8zfZdPBODMEgSab8bOPSxywKb6AFyonQE=",
    "Name" : "SUN TU PROMO NEW 2",
    "OnlineHost" : true,
    "Port" : 8080,
    "Proxy" : "",
    "ReverseProxy" : false,
    "ShowText" : false,
    "Text" : "",
    "UseDefaultProxy" : true
  }, {
    "Format" : 3,
    "ForwardHost" : false,
    "FullHost" : true,
    "Host" : "mi8hZ+6oPYHqqKIX2VS5Myfw79foMRtJ/Z25HeYw74AKS7LxopRaHx166TOc8psLVLjrgihFgdoGKMLu44n78Q==",
    "Name" : "SUN FIXED LOAD 1",
    "OnlineHost" : true,
    "Port" : 8080,
    "Proxy" : "",
    "ReverseProxy" : false,
    "ShowText" : false,
    "Text" : "",
    "UseDefaultProxy" : true
  }, {
    "Format" : 3,
    "ForwardHost" : false,
    "FullHost" : true,
    "Host" : "Eoiw2PCm/U5Wl58oInUEC23raddoCFkECdihhqcrBmIn3yWd57pSekN/Y73emLWZgKA7WMyQiFJKOf/3WDtd0g==",
    "Name" : "SUN FIXED LOAD 2",
    "OnlineHost" : true,
    "Port" : 8080,
    "Proxy" : "",
    "ReverseProxy" : false,
    "ShowText" : false,
    "Text" : "",
    "UseDefaultProxy" : true
  }, {
    "Format" : 1,
    "ForwardHost" : true,
    "FullHost" : false,
    "Host" : "8joqnAcSSobVXAGK2sb+IEmtWIXE6S78CoGo1cv6ROuuyMulKEjtsci1GgxyKh473RIT/OfmZDXSE6XWG8QdeA==",
    "Name" : "SMART/TNT GIGASTORIES 1",
    "OnlineHost" : true,
    "Port" : 8080,
    "Proxy" : "",
    "ReverseProxy" : false,
    "ShowText" : true,
    "Text" : "enjoy",
    "UseDefaultProxy" : true
  }, {
    "Format" : 1,
    "ForwardHost" : true,
    "FullHost" : false,
    "Host" : "da275S5WYPXCgdHr+LTMAVgZZPZWoZhYmtPYG3HnOANwk2V9+cC+VXk0Wwyug3vExoLX6o8ItJsTe5eE18y2rw==",
    "Name" : "SMART/TNT GIGASTORIES 2",
    "OnlineHost" : true,
    "Port" : 8080,
    "Proxy" : "",
    "ReverseProxy" : false,
    "ShowText" : true,
    "Text" : "enjoy",
    "UseDefaultProxy" : true
  }, {
    "Format" : 1,
    "ForwardHost" : true,
    "FullHost" : false,
    "Host" : "wWq3++i0H77QY7ZkDdVp1Z19hkRF/8jPWd/DmAI77lHxjifZLaiL7KSeSBgk6nscmsZclycdNV74ymdNM1HI7w==",
    "Name" : "TNT ML10 1",
    "OnlineHost" : true,
    "Port" : 8080,
    "Proxy" : "",
    "ReverseProxy" : false,
    "ShowText" : false,
    "Text" : "",
    "UseDefaultProxy" : true
  }, {
    "Format" : 1,
    "ForwardHost" : true,
    "FullHost" : false,
    "Host" : "EhrM5OU6rkjSoWv24A7tZ6bfQheuW/3W+IxUvNyU2KF/8JskIt6npIU57u5lm452j88iRkNxJqQj5eBY9yiYjQ==",
    "Name" : "TNT ML10 2",
    "OnlineHost" : true,
    "Port" : 8080,
    "Proxy" : "",
    "ReverseProxy" : false,
    "ShowText" : false,
    "Text" : "",
    "UseDefaultProxy" : true
  }, {
    "Format" : 0,
    "ForwardHost" : false,
    "FullHost" : false,
    "Host" : "Wnbx9cjE74sjL0Lx2hw+pLPA3HsjXewQdp2zfaDXUD1eIojrNYLpK2WjNRfHQTfs",
    "Name" : "SUN TU no blocking test",
    "OnlineHost" : false,
    "Port" : 8080,
    "Proxy" : "",
    "ReverseProxy" : false,
    "ShowText" : false,
    "Text" : "",
    "UseDefaultProxy" : true
  }, {
    "Format" : 1,
    "ForwardHost" : true,
    "FullHost" : false,
    "Host" : "FM00uKyUm53C15pr8/Ss/1/cbFqVVh0NE6a0NsMiYb/0a0ek0fn/UrXd8OFv0yZMQlrOPrVsLCKiaW8R3rqG1Q==",
    "Name" : "SMART/TNT GIGASTORIES 3",
    "OnlineHost" : true,
    "Port" : 8080,
    "Proxy" : "",
    "ReverseProxy" : false,
    "ShowText" : true,
    "Text" : "2gb/day",
    "UseDefaultProxy" : true
  }, {
    "Format" : 1,
    "ForwardHost" : true,
    "FullHost" : false,
    "Host" : "zGSv5/NBmDhaIli3osptlSCNZYPh3baYHO22T+X9FvmmCq6oxWq1jHMROOV3CxJ0Eh/jY5TUm092WIHDQCiBenJtirkhKrsYh+A9z1BMDFE=",
    "Name" : "SMART GIGAVIDEOS 1",
    "OnlineHost" : true,
    "Port" : 8080,
    "Proxy" : "",
    "ReverseProxy" : false,
    "ShowText" : false,
    "Text" : "",
    "UseDefaultProxy" : true
  }, {
    "Format" : 1,
    "ForwardHost" : true,
    "FullHost" : false,
    "Host" : "nKXSZSd8xZVR9WCJjDLicBBeD7KsjGs1u+W4ZUEgUbLA6b3NIfB5edNLt4OhrPtEaX+g3dhRLTHgcSsaE1Xfky6Mhk7XYSgHgEDK1Ylu74M=",
    "Name" : "NEW SMART GIGAVIDEOS",
    "OnlineHost" : true,
    "Port" : 8080,
    "Proxy" : "",
    "ReverseProxy" : false,
    "ShowText" : false,
    "Text" : "",
    "UseDefaultProxy" : true
  }, {
    "Format" : 1,
    "ForwardHost" : true,
    "FullHost" : false,
    "Host" : "lT6wJsQ/+Uz3rUufHiaoUnVJjry7+uIBdNTiygLbZh0T8X570ji/q6ZaMAWdVCi7zTT5b187I7fu9DWBTu7QGFtkrZ/LIRV4jh/fsNkyX4s=",
    "Name" : "SMART GIGAGAMES 1",
    "OnlineHost" : true,
    "Port" : 8080,
    "Proxy" : "",
    "ReverseProxy" : false,
    "ShowText" : false,
    "Text" : "",
    "UseDefaultProxy" : true
  }, {
    "Format" : 1,
    "ForwardHost" : true,
    "FullHost" : false,
    "Host" : "sMM+H00A07r3J/T0D1EKL+Tur3Ov/53iVNnsLf/J9+mj78h00DKVvkZS/m1iSmI2Sk1Yg/c8hdo8LT5eVToUpZ9Oa5qr/EAj9Ib+kWQyYIs=",
    "Name" : "SMART GIGAGAMES 2",
    "OnlineHost" : true,
    "Port" : 8080,
    "Proxy" : "",
    "ReverseProxy" : false,
    "ShowText" : false,
    "Text" : "",
    "UseDefaultProxy" : true
  }, {
    "Format" : 1,
    "ForwardHost" : true,
    "FullHost" : false,
    "Host" : "rH2UM0av09VkO/53iKCby+TEUdyFxd8uY++keMP2mxFpZKFQcxFksGzi5Ycn2GFhfCbaejRUxTZ2gmGtvZ6lPw==",
    "Name" : "LUZON STORIES 1",
    "OnlineHost" : true,
    "Port" : 8080,
    "Proxy" : "",
    "ReverseProxy" : false,
    "ShowText" : false,
    "Text" : "",
    "UseDefaultProxy" : true
  }, {
    "Format" : 1,
    "ForwardHost" : true,
    "FullHost" : false,
    "Host" : "Bs2ohj9fQpn7BkZH6m7q1vpBsgrIDpR8chz1hI5aYSeYVV6vCr0mk7up/crskrPpJWlAiSPaAFzsndj9zYiVKw==",
    "Name" : "LUZON STORIES 2",
    "OnlineHost" : true,
    "Port" : 8080,
    "Proxy" : "",
    "ReverseProxy" : false,
    "ShowText" : false,
    "Text" : "",
    "UseDefaultProxy" : true
  }, {
    "Format" : 1,
    "ForwardHost" : true,
    "FullHost" : false,
    "Host" : "cPss7KXcIe0uay9kaYFON7dw1l6tuqrf67hXN7mX/xHiAPnAPIlW4Lzfmkjr/EApP43GGSmKfQS9hOy9XnVrI4bMFVklbFV+GdpwIuryfjg=",
    "Name" : "GTM EASYSURF/GOSAKTO 1",
    "OnlineHost" : true,
    "Port" : 8080,
    "Proxy" : "",
    "ReverseProxy" : false,
    "ShowText" : false,
    "Text" : "",
    "UseDefaultProxy" : true
  }, {
    "Format" : 1,
    "ForwardHost" : true,
    "FullHost" : false,
    "Host" : "ZjQIVg7BHYIlG7JyrVznVQ5eV0DqcltBvFGmdE4TQixY7iNGH3Z3eRhmBdCwOxPY3WkwIX+m/9QUj/TEvYwKko6sa9B1QvzXa0Ip8QwVRJI=",
    "Name" : "GTM EASYSURF/GOSAKTO 2",
    "OnlineHost" : true,
    "Port" : 8080,
    "Proxy" : "",
    "ReverseProxy" : false,
    "ShowText" : false,
    "Text" : "",
    "UseDefaultProxy" : true
  }, {
    "Format" : 1,
    "ForwardHost" : true,
    "FullHost" : false,
    "Host" : "L0EEAziq0mqfumXx/jO/115gSbChmdXNbp8G8AtDip/r/LTLstaBIpczPtheHTBZwSDyjbVewNYM2ve0IBiwJA==",
    "Name" : "SUN FLP 3",
    "OnlineHost" : true,
    "Port" : 8080,
    "Proxy" : "",
    "ReverseProxy" : false,
    "ShowText" : false,
    "Text" : "",
    "UseDefaultProxy" : true
  }, {
    "Format" : 3,
    "ForwardHost" : true,
    "FullHost" : false,
    "Host" : "NiytV/GUiWP8nq3Ob+YpmbIOjCs4Bn39kU85Dro4mdKJH63ULQj8PPlFAXeAqbkfGq49Ctz1zRVqcqT+DO8Z7A==",
    "Name" : "SUN FLP 4",
    "OnlineHost" : true,
    "Port" : 8080,
    "Proxy" : "",
    "ReverseProxy" : false,
    "ShowText" : false,
    "Text" : "",
    "UseDefaultProxy" : true
  }, {
    "Format" : 0,
    "ForwardHost" : false,
    "FullHost" : false,
    "Host" : "gjqIGRbIZU+18UP7+c/u/Cwy0LVTT/CwVEgMoDue5UjOZkvjaq9OAD78x8Rec8Td",
    "Name" : "SMART/TNT/SUN-WILDRIFT",
    "OnlineHost" : false,
    "Port" : 8080,
    "Proxy" : "",
    "ReverseProxy" : false,
    "ShowText" : false,
    "Text" : "",
    "UseDefaultProxy" : true
  }, {
    "Format" : 5,
    "ForwardHost" : true,
    "FullHost" : false,
    "Host" : "nolsmZbCKYwUQfso3N5D2Vuy7tlNjq7fRxOD05v+zWT1oXRdzNN4ZWZBsZe6sg4y",
    "Name" : "DITO NO LOAD/NO PROMO",
    "OnlineHost" : true,
    "Port" : 8070,
    "Proxy" : "",
    "ReverseProxy" : false,
    "ShowText" : false,
    "Text" : "",
    "UseDefaultProxy" : true
  } ],
  "GuiCategories" : true,
  "GuiFlags" : true,
  "Changelogs" : "﻿<strong>\uD83D\uDC3C<font color=\"yellow\"> UNIVERSAL VPN HAS BEEN UPDATED</font>\uD83D\uDC3C</strong>\n<br>\n<strong>⭐<font color=\"red\">What's New?</font>⭐</strong>\n</font>\n<br>\n⭐<font color=\"green\">NEW UPDATED (PAYLOADS..BY REYMUND RUIZ ..co-owners CHRISTOPHER/SHERMAN/CHAD/MHIX</font>⭐\n<br>\n⭐<font color=\"red\">BY: UNIVERSAL OWNER: REYMUND RUIZ.....</font>⭐\n\n<br>\n<font color=\"green\">\n<br>\n\n⭐</strong>* VPN COMMON ERRORS & BASIC TROUBLESHOOTING *⭐</strong>\n\n</strong> \n</font>\n<br>\n<font color=\"green\">\n<br>\n\n\n1. WAITING TO SERVER REPLY ERROR\n\n</strong> \n</font>\n<font color=\"white\">\n\n<br>\n- Expired promo.\n<br>\n- Change server.\n<br>\n- Restart phone.\n<br>\n</strong> \n</font>\n<font color=\"green\">\n\n2. UNKNOWN STATE ERROR\n\n</strong> \n</font>\n<font color=\"white\">\n<br>\n- Wrong promo configuration.\n<br>\n- Expired promo.\n<br>\n- Change server.\n\n<br>\n</strong> \n</font>\n<font color=\"green\">\n\n3. TRANSPORT ERROR\n\n</strong> \n</font>\n<font color=\"white\">\n<br>\n- Wrong promo configuration.\n<br>\n- Expired promo.\n<br>\n- Change server.\n<br>\n\n</strong> \n</font>\n<font color=\"green\">\n\n4. DISCONNECTED SUCCESSFULLY\n\n</strong> \n</font>\n<font color=\"white\">\n<br>\n- Change server.\n<br>\n\n</strong> \n</font>\n<font color=\"green\">\n\n5. AUTH FAILED/ CHECK ACCOUNT DETAILS\n\n</strong> \n</font>\n<font color=\"white\">\n<br>\n\n- Wrong Spelling username or password.\n<br>\n- Expired account.\n<br>\n- Don't make spacing.\n<br>\n</strong> \n</font>\n<font color=\"green\">\n\n6. CRASH LOG ERROR/CAUSE OF ERROR\n\n</strong> \n</font>\n<font color=\"white\">\n<br>\n- Re-open or restart VPN app.\n<br>\n- Restart phone.\n<br>\n</strong> \n</font>\n<font color=\"green\">\n7. ALWAYS CONNECTING STATUS: \n</strong> \n</font>\n<font color=\"white\">\n<br>\n- Weak signal status.\n<br>\n- Weak data receive.\n<br>\n- Turn on and off airplane mode.\n<br>\n- Change server.\n<br>\n</strong> \n</font>\n<font color=\"green\">\n8. CLIENT VERIFICATION FAILED\n</strong> \n</font>\n<font color=\"white\">\n<br>\n\n- Set your date and time correctly.\n<br>\n</strong> \n</font>\n<font color=\"green\">\n9. PROXY ERROR\n</strong> \n</font>\n<font color=\"white\">\n\n<br>\n- Turn on and off airplane mode.\n<br>\n- Change server.\n\n<br>\n</strong> \n</font>\n<font color=\"green\">\n10. OTHER VPN STARTED OR VPN STOPPED\n\n</strong> \n</font>\n<font color=\"white\">\n<br>\n- Disable power saving mode.\n<br>\n- Allow vpn to run in background.\n\n<br>\nReminder: \n<br>\n\n</strong> \n</font>\n<font color=\"red\">\n\n⭐</strong> Make sure your VPN app is always up to date.⭐</strong></font>\n<br>\n\n<font color=\"yellow\">\n\n<br>\n\uD83D\uDD30<strong>Account Pricing</strong>\uD83D\uDD30\n</font>\n<br>\n<font color=\"blue\">\n<strong>Premium: </strong>P100.00\n<br>\n<strong>VIP: </strong>P150.00\n<br>\n<strong>Private: </strong>P200.00</font>\n<br>\n<br>\n\n<font color=\"yellow\">\n<strong>\uD83D\uDD30REMINDERS!\uD83D\uDD30</font></strong>\n<br><font color=\"red\">\n⚠️☢️NO DUAL LOGIN☢️⚠️\n<br>\n\uD83D\uDCF5To avoid account termination\uD83D\uDCF5</font>\n<br>\n\uD83C\uDFAD\uD83C\uDFAD\uD83C\uDFAD\uD83C\uDFAD\uD83C\uDFAD\uD83C\uDFAD\uD83C\uDFAD\uD83C\uDFAD\n<br>\n<br>\n\n<font color=\"yellow\">\n<strong>\n\uD83D\uDD30NOW HIRING!\uD83D\uDD30\n</font>\n\n<br><font color=\"red\">\n\uD83D\uDC65Sub-Admin\n<br>\n\uD83D\uDC65Resellers\n<br>\n\uD83D\uDC65Sub-Resellers</font>\n</strong>\n<br>\n<br>\n<i>\uD83D\uDC4DJoin <strong><font color=\"blue\">UNIVERSAL VPN Team </font></strong>\n<font color=\"yellow\"> now and earn extra income \uD83E\uDD11 upto\n</font> <strong>4k per week. </strong></i>\n<br>\n<br>\n\n⭐⭐\n<br>\n<font color=\"yellow\">\n\uD83D\uDD30LIKE US ON FACEBOOK\uD83D\uDD30\n</font>\n</strong>\n<br>\n<strong>FACEBOOK: \n<font color=\"red\">\nUNIVERSAL VPN Official</font>\n</strong>\n<br>\n<font color=\"blue\">https://www.facebook.com/Universal-VPN-Community-111577567022901/</font>\n\n<br>\n\n<font color=\"green\">\n\uD83D\uDC3CFOR MORE CONCERN, CONTACT:09057387851/09190784813</font>\n<br>\n\uD83D\uDCAC<strong>\n<font color=\"red\">UNIVERSAL OWNER/REYMUND RUIZ</font>\n</strong>\n\n\n<font color=\"blue\">https://https://www.facebook.com/reymund.ruiz.756</font>\n<br>\n\uD83D\uDCAC<strong>\n<font color=\"red\">UNIVERSAL OWNER/REYMUND RUIZ</font>\n</strong>\n\n<font color=\"blue\">https://www.facebook.com/reymund.ruiz.756</font>\n\n<br>\n\uD83D\uDCAC<strong>\n<font color=\"red\">UNIVERSAL DEVELOPER/OWNERS:by,REYMUND RUIZ</font>\n</strong>\n\n<font color=\"blue\">https://www.facebook.com/reymund.ruiz.756</font>\n\n\n<br>\n",
  "Version" : 12.2
}
